{"id":"58246","ean":"8421384085841","slug":"salchichon-bellota-iberico-hacienda-iberico-pieza","brand":"La Hacienda del ibérico","limit":999,"badges":{"is_water":false,"requires_age_check":false},"origin":"España","photos":[{"zoom":"https://prod-mercadona.imgix.net/images/7a3f85e00a980307697945aa0a11e884.jpg?fit=crop&h=1600&w=1600","regular":"https://prod-mercadona.imgix.net/images/7a3f85e00a980307697945aa0a11e884.jpg?fit=crop&h=600&w=600","thumbnail":"https://prod-mercadona.imgix.net/images/7a3f85e00a980307697945aa0a11e884.jpg?fit=crop&h=300&w=300","perspective":2},{"zoom":"https://prod-mercadona.imgix.net/images/890efe346a813733d135abc3bbc8bde4.jpg?fit=crop&h=1600&w=1600","regular":"https://prod-mercadona.imgix.net/images/890efe346a813733d135abc3bbc8bde4.jpg?fit=crop&h=600&w=600","thumbnail":"https://prod-mercadona.imgix.net/images/890efe346a813733d135abc3bbc8bde4.jpg?fit=crop&h=300&w=300","perspective":9}],"details":{"brand":"La Hacienda del ibérico","origin":"España","suppliers":[{"name":"INCARLOPSA"}],"legal_name":"Salchichón de bellota ibérico","description":"Salchichón de bellota ibérico La Hacienda del ibérico","counter_info":null,"danger_mentions":null,"alcohol_by_volume":null,"mandatory_mentions":"sin gluten, sin lactosa","production_variant":"Producto de peso variable: el contenido neto podrá oscilar entre 550 y 600 GR","usage_instructions":"Recomendamos sacar el producto de la bolsa 24 h antes de su consumo.","storage_instructions":"Una vez abierto conservar en el frigorífico y consumir antes de 7 días. Conservese en lugar fresco y seco."},"packaging":"Pieza","published":true,"share_url":"https://tienda.mercadona.es/product/58246/salchichon-bellota-iberico-hacienda-iberico-pieza","thumbnail":"https://prod-mercadona.imgix.net/images/7a3f85e00a980307697945aa0a11e884.jpg?fit=crop&h=300&w=300","categories":[{"id":4,"name":"Charcutería y quesos","level":0,"order":159,"categories":[{"id":51,"name":"Embutido curado","level":1,"order":159,"categories":[{"id":301,"name":"Salchichón","level":2,"order":159}]}]}],"extra_info":[null],"display_name":"Salchichón de bellota ibérico La Hacienda del ibérico","is_variable_weight":true,"price_instructions":{"iva":10,"is_new":false,"is_pack":false,"pack_size":null,"unit_name":null,"unit_size":0.445,"bulk_price":"20.90","unit_price":"9.30","approx_size":true,"size_format":"kg","total_units":null,"unit_selector":true,"bunch_selector":false,"drained_weight":null,"selling_method":0,"price_decreased":false,"reference_price":"20.900","min_bunch_amount":1.0,"reference_format":"kg","increment_bunch_amount":1.0},"nutrition_information":{"allergens":null,"ingredients":"Carne y grasa de cerdo  de bellota ibérico, sal, dextrosa, proteína de <strong>soja</strong>, especias, aromas, estabilizantes (E-451i, E-450i), potenciador  del sabor (E-621), antioxidante (E-301) y conservadores (E-252, E-250). Tripa  natural de cerdo."}}