{"id":"84710","ean":"8425514214583","slug":"berlina-glace-paquete","brand":null,"limit":999,"badges":{"is_water":false,"requires_age_check":false},"origin":"ESPAÑA","photos":[{"zoom":"https://prod-mercadona.imgix.net/images/6b6e2a3db8d4d2f2764868e765c97b35.jpg?fit=crop&h=1600&w=1600","regular":"https://prod-mercadona.imgix.net/images/6b6e2a3db8d4d2f2764868e765c97b35.jpg?fit=crop&h=600&w=600","thumbnail":"https://prod-mercadona.imgix.net/images/6b6e2a3db8d4d2f2764868e765c97b35.jpg?fit=crop&h=300&w=300","perspective":1},{"zoom":"https://prod-mercadona.imgix.net/images/0c18ad8613ef2b68e7f6115b2bc26b93.jpg?fit=crop&h=1600&w=1600","regular":"https://prod-mercadona.imgix.net/images/0c18ad8613ef2b68e7f6115b2bc26b93.jpg?fit=crop&h=600&w=600","thumbnail":"https://prod-mercadona.imgix.net/images/0c18ad8613ef2b68e7f6115b2bc26b93.jpg?fit=crop&h=300&w=300","perspective":9}],"details":{"brand":null,"origin":"ESPAÑA","suppliers":[{"name":"COBOPA, S.L."},{"name":"FRIMAR PANADEROS, S.L."},{"name":"PANAMAR BAKERY GROUP, S.L."},{"name":"PANAMAR PANADEROS, S.L."}],"legal_name":"PRODUCTO DE BOLLERÍA FRITA GLASEADO. BERLINA GLACE (TREN 4 UD)","description":"Berlina glacé","counter_info":null,"danger_mentions":null,"alcohol_by_volume":null,"mandatory_mentions":null,"production_variant":null,"usage_instructions":"Producto listo para consumo.","storage_instructions":"Conservar en lugar fresco y seco."},"packaging":"Paquete","published":true,"share_url":"https://tienda.mercadona.es/product/84710/berlina-glace-paquete","thumbnail":"https://prod-mercadona.imgix.net/images/6b6e2a3db8d4d2f2764868e765c97b35.jpg?fit=crop&h=300&w=300","categories":[{"id":5,"name":"Panadería y pastelería","level":0,"order":511,"categories":[{"id":65,"name":"Bollería de horno","level":1,"order":511,"categories":[{"id":330,"name":"Bollería dulce","level":2,"order":511}]}]}],"extra_info":["Consumir preferentemente antes de 24 horas desde su entrega."],"display_name":"Berlina glacé","is_variable_weight":false,"price_instructions":{"iva":10,"is_new":false,"is_pack":false,"pack_size":null,"unit_name":"ud.","unit_size":0.2,"bulk_price":"6.75","unit_price":"1.35","approx_size":false,"size_format":"kg","total_units":4,"unit_selector":true,"bunch_selector":false,"drained_weight":null,"selling_method":0,"price_decreased":false,"reference_price":"6.750","min_bunch_amount":1.0,"reference_format":"kg","increment_bunch_amount":1.0},"nutrition_information":{"allergens":"Contiene <strong>huevos y productos a base de huevo</strong>. Contiene <strong>leche y sus derivados (incluida la lactosa)</strong>. Contiene <strong>soja y productos a base de soja</strong>. Contiene <strong>huevos y productos a base de huevo</strong>. Contiene <strong>leche y sus derivados (incluida la lactosa)</strong>. Contiene <strong>cereales que contengan gluten</strong>. Contiene <strong>soja y productos a base de soja</strong>.","ingredients":"Harina de <strong>trigo</strong>, cobertura (20%) (azúcar, agua, jarabe de glucosa, emulgente (E471), conservador (E202), estabilizantes (E410, E412), acidulante (ácido cítrico), aroma), grasas y aceites vegetales (palma), agua, <strong>huevo</strong>, azúcar, levadura, gluten de <strong>trigo</strong>, emulgentes (lecitina de <strong>soja</strong>, E471, E481), gasificantes (E450, E500), sal, almidón de <strong>trigo</strong>, harina de <strong>soja</strong>, sólidos <strong>lácteos</strong>, estabilizante (E466), colorante (beta-caroteno). Puede contener trazas de <strong>frutos</strong> de <strong>cáscara</strong>."}}