{"id":"34193","ean":"8480000341938","slug":"pipas-girasol-naturales-hacendado-peladas-paquete","brand":"Hacendado","limit":999,"badges":{"is_water":false,"requires_age_check":false},"origin":"Bulgaria","photos":[{"zoom":"https://prod-mercadona.imgix.net/images/3f67bc4f82159cd67734c4125891318d.jpg?fit=crop&h=1600&w=1600","regular":"https://prod-mercadona.imgix.net/images/3f67bc4f82159cd67734c4125891318d.jpg?fit=crop&h=600&w=600","thumbnail":"https://prod-mercadona.imgix.net/images/3f67bc4f82159cd67734c4125891318d.jpg?fit=crop&h=300&w=300","perspective":2},{"zoom":"https://prod-mercadona.imgix.net/images/5a86d0e655248f4a63e62c2b3f61b057.jpg?fit=crop&h=1600&w=1600","regular":"https://prod-mercadona.imgix.net/images/5a86d0e655248f4a63e62c2b3f61b057.jpg?fit=crop&h=600&w=600","thumbnail":"https://prod-mercadona.imgix.net/images/5a86d0e655248f4a63e62c2b3f61b057.jpg?fit=crop&h=300&w=300","perspective":9}],"details":{"brand":"Hacendado","origin":"Bulgaria","suppliers":[{"name":"IMPORTACO CASA PONS S.A.U."}],"legal_name":"PIPA GIRASOL NATURAL","description":"Pipas girasol naturales Hacendado peladas","counter_info":null,"danger_mentions":null,"alcohol_by_volume":null,"mandatory_mentions":"Producto natural y sin conservantes. Envasado en atmósfera protectora. LOS FRUTOS SECOS POR SU TAMAÑO NO LOS DEBEN CONSUMIR MENORES DE 5 AÑOS.","production_variant":null,"usage_instructions":"Una vez abierto el envase, conservarlo cerrado y consumir el producto preferentemente en el plazo de una semana.","storage_instructions":"Proteger de la luz. Conservar en lugar fresco y seco."},"packaging":"Paquete","published":true,"share_url":"https://tienda.mercadona.es/product/34193/pipas-girasol-naturales-hacendado-peladas-paquete","thumbnail":"https://prod-mercadona.imgix.net/images/3f67bc4f82159cd67734c4125891318d.jpg?fit=crop&h=300&w=300","categories":[{"id":15,"name":"Aperitivos","level":0,"order":9,"categories":[{"id":133,"name":"Frutos secos y fruta desecada","level":1,"order":9,"categories":[{"id":479,"name":"Frutos secos","level":2,"order":9}]}]}],"extra_info":[null],"display_name":"Pipas girasol naturales Hacendado peladas","is_variable_weight":false,"price_instructions":{"iva":0,"is_new":false,"is_pack":false,"pack_size":null,"unit_name":null,"unit_size":0.2,"bulk_price":"5.55","unit_price":"1.11","approx_size":false,"size_format":"kg","total_units":null,"unit_selector":true,"bunch_selector":false,"drained_weight":null,"selling_method":0,"price_decreased":false,"reference_price":"5.550","min_bunch_amount":1.0,"reference_format":"kg","increment_bunch_amount":1.0},"nutrition_information":{"allergens":null,"ingredients":"Pipas de girasol peladas. </p><strong>TRAZAS DE CACAHUETE, FRUTOS DE CÁSCARA Y SOJA.</strong>"}}