{"id":"86340","ean":"8414601138550","slug":"vino-tinto-do-mancha-fidencio-botella","brand":"Fidencio","limit":999,"badges":{"is_water":false,"requires_age_check":true},"origin":null,"photos":[{"zoom":"https://prod-mercadona.imgix.net/images/4024d09f60ed7292de7e80000d777d41.jpg?fit=crop&h=1600&w=1600","regular":"https://prod-mercadona.imgix.net/images/4024d09f60ed7292de7e80000d777d41.jpg?fit=crop&h=600&w=600","thumbnail":"https://prod-mercadona.imgix.net/images/4024d09f60ed7292de7e80000d777d41.jpg?fit=crop&h=300&w=300","perspective":1},{"zoom":"https://prod-mercadona.imgix.net/images/5dbd10c79f0afccb0843561a4f8f18fc.jpg?fit=crop&h=1600&w=1600","regular":"https://prod-mercadona.imgix.net/images/5dbd10c79f0afccb0843561a4f8f18fc.jpg?fit=crop&h=600&w=600","thumbnail":"https://prod-mercadona.imgix.net/images/5dbd10c79f0afccb0843561a4f8f18fc.jpg?fit=crop&h=300&w=300","perspective":9}],"status":null,"details":{"brand":"Fidencio","origin":null,"suppliers":[{"name":"Virgen de las Viñas Bodega y Almazara Sociedad Cooperativa de Castilla la Mancha"}],"legal_name":"Vino tinto","description":"Vino tinto D.O La Mancha Fidencio","counter_info":null,"danger_mentions":"","alcohol_by_volume":"13.0º","mandatory_mentions":"Consumo moderado","production_variant":"","usage_instructions":"","storage_instructions":"Conservese en lugar fresco y protegido de la luz solar"},"is_bulk":false,"packaging":"Botella","published":true,"share_url":"https://tienda.mercadona.es/product/86340/vino-tinto-do-mancha-fidencio-botella","thumbnail":"https://prod-mercadona.imgix.net/images/4024d09f60ed7292de7e80000d777d41.jpg?fit=crop&h=300&w=300","categories":[{"id":19,"name":"Bodega","level":0,"order":15,"categories":[{"id":169,"name":"Vino tinto","level":1,"order":15,"categories":[{"id":566,"name":"Castilla la Mancha","level":2,"order":15}]}]}],"extra_info":[null],"display_name":"Vino tinto D.O La Mancha Fidencio","unavailable_from":null,"is_variable_weight":false,"price_instructions":{"iva":null,"is_new":false,"is_pack":false,"pack_size":null,"unit_name":null,"unit_size":0.75,"bulk_price":"1.73","unit_price":"1.30","approx_size":false,"size_format":"l","total_units":null,"unit_selector":true,"bunch_selector":false,"drained_weight":null,"selling_method":0,"tax_percentage":"21.000","price_decreased":false,"reference_price":"1.734","min_bunch_amount":1.0,"reference_format":"L","previous_unit_price":null,"increment_bunch_amount":1.0},"unavailable_weekdays":[],"nutrition_information":{"allergens":" <strong>x99</strong>.","ingredients":"Uvas, mosto de uva concentrado, correctores de la acidez (contiene ácido tartárico y/o ácido láctico), agentes estabilizantes ( contiene ácido metatartárico y/o goma arábiga),  conservador  (<strong>dióxido de azufre (sulfitos)</strong>, dicarbonato de dimetilo)"}}