{"id":"4435","ean":"8436569261323","slug":"pieza-solomillo-vacuno-anojo-horno-pieza","brand":null,"limit":999,"badges":{"is_water":false,"requires_age_check":false},"origin":null,"photos":[{"zoom":"https://prod-mercadona.imgix.net/images/6cc6b29f90abec34d71499ac2d037bef.jpg?fit=crop&h=1600&w=1600","regular":"https://prod-mercadona.imgix.net/images/6cc6b29f90abec34d71499ac2d037bef.jpg?fit=crop&h=600&w=600","thumbnail":"https://prod-mercadona.imgix.net/images/6cc6b29f90abec34d71499ac2d037bef.jpg?fit=crop&h=300&w=300","perspective":1},{"zoom":"https://prod-mercadona.imgix.net/images/a30bd5df6960c57f0f2906932b0db219.jpg?fit=crop&h=1600&w=1600","regular":"https://prod-mercadona.imgix.net/images/a30bd5df6960c57f0f2906932b0db219.jpg?fit=crop&h=600&w=600","thumbnail":"https://prod-mercadona.imgix.net/images/a30bd5df6960c57f0f2906932b0db219.jpg?fit=crop&h=300&w=300","perspective":9}],"details":{"brand":null,"origin":null,"suppliers":[{"name":"Elaborados Cárnicos Medina S.A.U."}],"legal_name":"PIEZA SOLOMILLO","description":"Pieza solomillo de vacuno añojo para horno","counter_info":null,"danger_mentions":null,"alcohol_by_volume":null,"mandatory_mentions":"Envasado al vacío","production_variant":"Producto de peso variable, el contenido neto puede oscilar entre 750g y 1200g","usage_instructions":"Cocinar completamente antes de su consumo","storage_instructions":"Conservar de 0 a 5C. Una vez abierto consumir en 24 horas"},"is_bulk":true,"packaging":"Pieza","published":true,"share_url":"https://tienda.mercadona.es/product/4435/pieza-solomillo-vacuno-anojo-horno-pieza","thumbnail":"https://prod-mercadona.imgix.net/images/6cc6b29f90abec34d71499ac2d037bef.jpg?fit=crop&h=300&w=300","categories":[{"id":3,"name":"Carne","level":0,"order":17,"categories":[{"id":40,"name":"Vacuno","level":1,"order":17,"categories":[{"id":283,"name":"Vacuno","level":2,"order":17}]}]}],"extra_info":[null],"display_name":"Pieza solomillo de vacuno añojo para horno","unavailable_from":"2023-12-30T23:00:00+00:00","is_variable_weight":true,"price_instructions":{"iva":10,"is_new":false,"is_pack":false,"pack_size":null,"unit_name":null,"unit_size":1.1,"bulk_price":"36.00","unit_price":"39.60","approx_size":true,"size_format":"kg","total_units":null,"unit_selector":true,"bunch_selector":false,"drained_weight":null,"selling_method":0,"price_decreased":false,"reference_price":"36.000","min_bunch_amount":1.0,"reference_format":"kg","previous_unit_price":null,"increment_bunch_amount":1.0},"unavailable_weekdays":[],"nutrition_information":{"allergens":null,"ingredients":""}}