{"id":"3387","ean":"2105400033875","slug":"media-calabaza-cacahuete-12-pieza","brand":null,"limit":999,"badges":{"is_water":false,"requires_age_check":false},"origin":"","photos":[{"zoom":"https://prod-mercadona.imgix.net/images/356901cd17a68ad6bdb190379250f206.jpg?fit=crop&h=1600&w=1600","regular":"https://prod-mercadona.imgix.net/images/356901cd17a68ad6bdb190379250f206.jpg?fit=crop&h=600&w=600","thumbnail":"https://prod-mercadona.imgix.net/images/356901cd17a68ad6bdb190379250f206.jpg?fit=crop&h=300&w=300","perspective":10},{"zoom":"https://prod-mercadona.imgix.net/images/12996ca7d80dd06cfcc0c80275fd21aa.jpg?fit=crop&h=1600&w=1600","regular":"https://prod-mercadona.imgix.net/images/12996ca7d80dd06cfcc0c80275fd21aa.jpg?fit=crop&h=600&w=600","thumbnail":"https://prod-mercadona.imgix.net/images/12996ca7d80dd06cfcc0c80275fd21aa.jpg?fit=crop&h=300&w=300","perspective":7}],"details":{"brand":null,"origin":"","suppliers":[],"legal_name":"","description":"Media calabaza cacahuete","counter_info":null,"danger_mentions":"","alcohol_by_volume":"","mandatory_mentions":"","production_variant":"","usage_instructions":"","storage_instructions":""},"packaging":"1/2 Pieza","published":true,"share_url":"https://tienda.mercadona.es/product/3387/media-calabaza-cacahuete-12-pieza","thumbnail":"https://prod-mercadona.imgix.net/images/356901cd17a68ad6bdb190379250f206.jpg?fit=crop&h=300&w=300","categories":[{"id":1,"name":"Fruta y verdura","level":0,"order":304,"categories":[{"id":29,"name":"Verdura","level":1,"order":304,"categories":[{"id":268,"name":"Otras verduras y hortalizas","level":2,"order":304}]}]}],"extra_info":[null],"display_name":"Media calabaza cacahuete","is_variable_weight":false,"price_instructions":{"iva":0,"is_new":false,"is_pack":false,"pack_size":null,"unit_name":null,"unit_size":0.65,"bulk_price":"1.78","unit_price":"1.16","approx_size":true,"size_format":"kg","total_units":null,"unit_selector":true,"bunch_selector":false,"drained_weight":null,"selling_method":0,"price_decreased":false,"reference_price":"1.780","min_bunch_amount":1.0,"reference_format":"kg","increment_bunch_amount":1.0},"nutrition_information":{"allergens":"","ingredients":""}}