{"id":"26496","ean":"8480000264961","slug":"vinagre-balsamico-modena-hacendado-botella","brand":"Hacendado","limit":999,"badges":{"is_water":false,"requires_age_check":false},"origin":"España","photos":[{"zoom":"https://prod-mercadona.imgix.net/images/f65c196d0aae6388f9e6852c381f8da4.jpg?fit=crop&h=1600&w=1600","regular":"https://prod-mercadona.imgix.net/images/f65c196d0aae6388f9e6852c381f8da4.jpg?fit=crop&h=600&w=600","thumbnail":"https://prod-mercadona.imgix.net/images/f65c196d0aae6388f9e6852c381f8da4.jpg?fit=crop&h=300&w=300","perspective":2},{"zoom":"https://prod-mercadona.imgix.net/images/e917afc2d38d943c1eb08ac7b024ffa3.jpg?fit=crop&h=1600&w=1600","regular":"https://prod-mercadona.imgix.net/images/e917afc2d38d943c1eb08ac7b024ffa3.jpg?fit=crop&h=600&w=600","thumbnail":"https://prod-mercadona.imgix.net/images/e917afc2d38d943c1eb08ac7b024ffa3.jpg?fit=crop&h=300&w=300","perspective":9}],"details":{"brand":"Hacendado","origin":"España","suppliers":[{"name":"J.R. Sabater, S.A."}],"legal_name":"Vinagre Balsámico de Modena / Aceto balsamico di Modena Indicación Geográfica Protegida","description":"Vinagre balsámico de Módena Hacendado","counter_info":null,"danger_mentions":"","alcohol_by_volume":null,"mandatory_mentions":"Acidez 6%. Certificado da Organismo di Controllo autorizzato dal Ministero competente.Lugar de envasado : nº CSQA 217121","production_variant":"","usage_instructions":"","storage_instructions":""},"is_bulk":false,"packaging":"Botella","published":true,"share_url":"https://tienda.mercadona.es/product/26496/vinagre-balsamico-modena-hacendado-botella","thumbnail":"https://prod-mercadona.imgix.net/images/f65c196d0aae6388f9e6852c381f8da4.jpg?fit=crop&h=300&w=300","categories":[{"id":12,"name":"Aceite, especias y salsas","level":0,"order":7,"categories":[{"id":112,"name":"Aceite, vinagre y sal","level":1,"order":7,"categories":[{"id":422,"name":"Vinagre y otros aderezos","level":2,"order":7}]}]}],"extra_info":[null],"display_name":"Vinagre balsámico de Módena Hacendado","unavailable_from":null,"is_variable_weight":false,"price_instructions":{"iva":10,"is_new":false,"is_pack":false,"pack_size":null,"unit_name":null,"unit_size":0.5,"bulk_price":"5.00","unit_price":"2.50","approx_size":false,"size_format":"l","total_units":null,"unit_selector":true,"bunch_selector":false,"drained_weight":null,"selling_method":0,"price_decreased":false,"reference_price":"5.000","min_bunch_amount":1.0,"reference_format":"L","previous_unit_price":null,"increment_bunch_amount":1.0},"unavailable_weekdays":[],"nutrition_information":{"allergens":"Contiene <strong>dióxido de azufre y sulfitos</strong>.","ingredients":"Vinagre de vino, mosto de uva concentrado (<strong>sulfitos</strong>), colorante Caramelo E-150d."}}