{"id":"22311","ean":"8480000223111","slug":"natillas-proteinas-sabor-vainilla-hacendado-12-g-proteinas-pack-4","brand":"Hacendado","limit":999,"badges":{"is_water":false,"requires_age_check":false},"origin":null,"photos":[{"zoom":"https://prod-mercadona.imgix.net/images/403d8051a4c86676bfd5d8784a6cd76f.jpg?fit=crop&h=1600&w=1600","regular":"https://prod-mercadona.imgix.net/images/403d8051a4c86676bfd5d8784a6cd76f.jpg?fit=crop&h=600&w=600","thumbnail":"https://prod-mercadona.imgix.net/images/403d8051a4c86676bfd5d8784a6cd76f.jpg?fit=crop&h=300&w=300","perspective":1},{"zoom":"https://prod-mercadona.imgix.net/images/5408ec9575484a25faeb07476f7bcbc7.jpg?fit=crop&h=1600&w=1600","regular":"https://prod-mercadona.imgix.net/images/5408ec9575484a25faeb07476f7bcbc7.jpg?fit=crop&h=600&w=600","thumbnail":"https://prod-mercadona.imgix.net/images/5408ec9575484a25faeb07476f7bcbc7.jpg?fit=crop&h=300&w=300","perspective":9}],"details":{"brand":"Hacendado","origin":null,"suppliers":[{"name":"EURIAL ULTRA FRAIS S.A.S.U"}],"legal_name":"Especialidad lactea sabor vainilla, con edulcorantes","description":"Natillas +Proteínas sabor vainilla Hacendado 12 g proteínas","counter_info":null,"danger_mentions":null,"alcohol_by_volume":null,"mandatory_mentions":null,"production_variant":null,"usage_instructions":null,"storage_instructions":"Consérvese en frío a + 6C máximo."},"packaging":"Pack-4","published":true,"share_url":"https://tienda.mercadona.es/product/22311/natillas-proteinas-sabor-vainilla-hacendado-12-g-proteinas-pack-4","thumbnail":"https://prod-mercadona.imgix.net/images/403d8051a4c86676bfd5d8784a6cd76f.jpg?fit=crop&h=300&w=300","categories":[{"id":11,"name":"Postres y yogures","level":0,"order":594,"categories":[{"id":110,"name":"Flan y natillas","level":1,"order":594,"categories":[{"id":418,"name":"Natillas","level":2,"order":594}]},{"id":111,"name":"Gelatina y otros postres","level":1,"order":594,"categories":[{"id":419,"name":"Otros postres","level":2,"order":594}]}]}],"extra_info":[null],"display_name":"Natillas +Proteínas sabor vainilla Hacendado 12 g proteínas","is_variable_weight":false,"price_instructions":{"iva":10,"is_new":false,"is_pack":true,"pack_size":0.12,"unit_name":"ud.","unit_size":0.48,"bulk_price":"3.85","unit_price":"1.85","approx_size":false,"size_format":"kg","total_units":4,"unit_selector":true,"bunch_selector":false,"drained_weight":null,"selling_method":0,"price_decreased":false,"reference_price":"3.855","min_bunch_amount":1.0,"reference_format":"kg","increment_bunch_amount":1.0},"nutrition_information":{"allergens":null,"ingredients":"<strong>Leche</strong> desnatada, agua, Proteinas de <strong>leche</strong> , nata (<strong>Leche</strong>), almidon modificado, aroma, corrector de acidez : citrato de sodio, espesantes : carragenanos, edulcorantes : acesulfame potásico y sucralosa . No contienen azucares anadidos* (*contiene azucares naturalmente presentes)"}}