{"id":"5046","ean":"8436047158428","slug":"lomo-cerdo-adobado-familiar-bandeja","brand":null,"limit":999,"badges":{"is_water":false,"requires_age_check":false},"origin":null,"photos":[{"zoom":"https://prod-mercadona.imgix.net/images/bfa3ccdb4f4f5a30e206bdaabc8af271.jpg?fit=crop&h=1600&w=1600","regular":"https://prod-mercadona.imgix.net/images/bfa3ccdb4f4f5a30e206bdaabc8af271.jpg?fit=crop&h=600&w=600","thumbnail":"https://prod-mercadona.imgix.net/images/bfa3ccdb4f4f5a30e206bdaabc8af271.jpg?fit=crop&h=300&w=300","perspective":2},{"zoom":"https://prod-mercadona.imgix.net/images/ed644546f4b1da7d9a19ca4fd8be9b43.jpg?fit=crop&h=1600&w=1600","regular":"https://prod-mercadona.imgix.net/images/ed644546f4b1da7d9a19ca4fd8be9b43.jpg?fit=crop&h=600&w=600","thumbnail":"https://prod-mercadona.imgix.net/images/ed644546f4b1da7d9a19ca4fd8be9b43.jpg?fit=crop&h=300&w=300","perspective":9}],"details":{"brand":null,"origin":null,"suppliers":[{"name":"Coopecarn Girona S.L.U"}],"legal_name":"Lomo adobado familiar. Preparado de carne adobado","description":"Lomo de cerdo adobado familiar","counter_info":null,"danger_mentions":null,"alcohol_by_volume":null,"mandatory_mentions":"Envasado en atmósfera protectora. Preparado de carne adobado con agua añadida.","production_variant":null,"usage_instructions":"Cocinar completamente antes de su consumo. Cocinar en sartén/plancha a fuego fuerte. Para: plancha, freir","storage_instructions":"Conservar de 0 a 4C.  Una vez abierto el envase consumir en 48 horas."},"packaging":"Bandeja","published":true,"share_url":"https://tienda.mercadona.es/product/5046/lomo-cerdo-adobado-familiar-bandeja","thumbnail":"https://prod-mercadona.imgix.net/images/bfa3ccdb4f4f5a30e206bdaabc8af271.jpg?fit=crop&h=300&w=300","categories":[{"id":3,"name":"Carne","level":0,"order":17,"categories":[{"id":37,"name":"Cerdo","level":1,"order":17,"categories":[{"id":280,"name":"Cerdo","level":2,"order":17}]},{"id":45,"name":"Empanados y elaborados","level":1,"order":17,"categories":[{"id":288,"name":"Empanados y elaborados","level":2,"order":17}]}]}],"extra_info":[null],"display_name":"Lomo de cerdo adobado familiar","is_variable_weight":true,"price_instructions":{"iva":10,"is_new":false,"is_pack":false,"pack_size":null,"unit_name":null,"unit_size":0.9,"bulk_price":"6.50","unit_price":"5.85","approx_size":true,"size_format":"kg","total_units":null,"unit_selector":true,"bunch_selector":false,"drained_weight":null,"selling_method":0,"price_decreased":false,"reference_price":"6.500","min_bunch_amount":1.0,"reference_format":"kg","previous_unit_price":null,"increment_bunch_amount":1.0},"nutrition_information":{"allergens":"Libre de <strong>ml</strong>.","ingredients":"Lomo de cerdo (90 %), agua, sal, azúcar, aromas, especias, pimentón, ajo, antioxidante (E-301), conservador (E-250)."}}