{"id":"23851","ean":"8480000238511","slug":"helado-vegetal-mini-triple-chocolate-base-anacardo-hacendado-caja","brand":"Hacendado","limit":999,"badges":{"is_water":false,"requires_age_check":false},"origin":"Italia","photos":[{"zoom":"https://prod-mercadona.imgix.net/images/8a6cf005c45b575be15fb63b39b6c93a.jpg?fit=crop&h=1600&w=1600","regular":"https://prod-mercadona.imgix.net/images/8a6cf005c45b575be15fb63b39b6c93a.jpg?fit=crop&h=600&w=600","thumbnail":"https://prod-mercadona.imgix.net/images/8a6cf005c45b575be15fb63b39b6c93a.jpg?fit=crop&h=300&w=300","perspective":1},{"zoom":"https://prod-mercadona.imgix.net/images/3c3dd2947a3d20433cd8b0d7954ecbe4.jpg?fit=crop&h=1600&w=1600","regular":"https://prod-mercadona.imgix.net/images/3c3dd2947a3d20433cd8b0d7954ecbe4.jpg?fit=crop&h=600&w=600","thumbnail":"https://prod-mercadona.imgix.net/images/3c3dd2947a3d20433cd8b0d7954ecbe4.jpg?fit=crop&h=300&w=300","perspective":9}],"details":{"brand":"Hacendado","origin":"Italia","suppliers":[{"name":"V.B.S. s. p.a."}],"legal_name":"HELADO VEGETAL A BASE DE ANACARDO, DE CHOCOLATE, CON COBERTURA (34%) Y ANACARDOS TOSTADOS Y PICADOS","description":"Helado vegetal mini triple chocolate a base de anacardo Hacendado","counter_info":null,"danger_mentions":null,"alcohol_by_volume":null,"mandatory_mentions":"100% vegetal. Sin proteína de la leche de vaca. Sin Gluten","production_variant":null,"usage_instructions":null,"storage_instructions":"Conservar a una temperatura no superior a -18C."},"packaging":"Caja","published":true,"share_url":"https://tienda.mercadona.es/product/23851/helado-vegetal-mini-triple-chocolate-base-anacardo-hacendado-caja","thumbnail":"https://prod-mercadona.imgix.net/images/8a6cf005c45b575be15fb63b39b6c93a.jpg?fit=crop&h=300&w=300","categories":[{"id":17,"name":"Congelados","level":0,"order":213,"categories":[{"id":154,"name":"Helados","level":1,"order":213,"categories":[{"id":894,"name":"Bombones","level":2,"order":213},{"id":521,"name":"Cucuruchos y bombones","level":2,"order":213}]}]}],"extra_info":[null],"display_name":"Helado vegetal mini triple chocolate a base de anacardo Hacendado","is_variable_weight":false,"price_instructions":{"iva":10,"is_new":false,"is_pack":false,"pack_size":0.0815,"unit_name":"ud.","unit_size":0.326,"bulk_price":"9.06","unit_price":"2.90","approx_size":false,"size_format":"l","total_units":4,"unit_selector":true,"bunch_selector":false,"drained_weight":null,"selling_method":0,"price_decreased":false,"reference_price":"9.063","min_bunch_amount":1.0,"reference_format":"L","increment_bunch_amount":1.0},"nutrition_information":{"allergens":null,"ingredients":"Bebida de ANACARDOS (33%)(agua, pasta de ANACARDOS (0,6%)), chocolate (26%)(pasta de cacao, azúcar, jarabe de glucosa, ANACARDOS tostados y picados (5%), maltodextrina, agua, chocolate negro en polvo (1,6%), cacao magro, dextrosa, estabilizantes: mono y diglicéridos de ácido grasos  alginato de sodio  harina de semillas de algarroba  goma guar, proteína de guisante, aromas, sal. Puede contener otros FRUTOS DE CÁSCARA."}}