{"id":"29007","ean":"8480000290076","slug":"bicarbonato-sodico-hacendado-paquete","brand":"Hacendado","limit":999,"badges":{"is_water":false,"requires_age_check":false},"origin":"España","photos":[{"zoom":"https://prod-mercadona.imgix.net/images/ed1ebfa8c76af67dc21a385de31fc778.jpg?fit=crop&h=1600&w=1600","regular":"https://prod-mercadona.imgix.net/images/ed1ebfa8c76af67dc21a385de31fc778.jpg?fit=crop&h=600&w=600","thumbnail":"https://prod-mercadona.imgix.net/images/ed1ebfa8c76af67dc21a385de31fc778.jpg?fit=crop&h=300&w=300","perspective":2},{"zoom":"https://prod-mercadona.imgix.net/images/744f77c11f94754f4827f3639e86df48.jpg?fit=crop&h=1600&w=1600","regular":"https://prod-mercadona.imgix.net/images/744f77c11f94754f4827f3639e86df48.jpg?fit=crop&h=600&w=600","thumbnail":"https://prod-mercadona.imgix.net/images/744f77c11f94754f4827f3639e86df48.jpg?fit=crop&h=300&w=300","perspective":6},{"zoom":"https://prod-mercadona.imgix.net/images/dbfc00ebc88dc335dfc136c5db359389.jpg?fit=crop&h=1600&w=1600","regular":"https://prod-mercadona.imgix.net/images/dbfc00ebc88dc335dfc136c5db359389.jpg?fit=crop&h=600&w=600","thumbnail":"https://prod-mercadona.imgix.net/images/dbfc00ebc88dc335dfc136c5db359389.jpg?fit=crop&h=300&w=300","perspective":5}],"details":{"brand":"Hacendado","origin":"España","suppliers":[{"name":"JESÚS NAVARRO, S.A."}],"legal_name":"Bicarbonato de Sodio","description":"Bicarbonato sódico Hacendado","counter_info":null,"danger_mentions":null,"alcohol_by_volume":null,"mandatory_mentions":null,"production_variant":null,"usage_instructions":"USOS TRADICIONALES: Gasificante en repostería: dosis según receta a utilizar. Antiácido: disuelve 1 cucharadita (7g) en 1 vaso de agua (250 ml). Elimina malos olores: En el frigorífico pon 1 cucharada en un platito. En el lavavajillas añade 1 cucharada después de cada lavado. Para lavar fruta / verdura: Mezcla una cucharada en 1L de agua y sumerge la fruta / verdura 10 min. Previene la formación de cal en la lavadora: Pon un lavado sin ropa con agua fría y 4 cucharadas de bicarbonato una vez al mes.","storage_instructions":"Conservar en lugar seco."},"packaging":"Paquete","published":true,"share_url":"https://tienda.mercadona.es/product/29007/bicarbonato-sodico-hacendado-paquete","thumbnail":"https://prod-mercadona.imgix.net/images/ed1ebfa8c76af67dc21a385de31fc778.jpg?fit=crop&h=300&w=300","categories":[{"id":12,"name":"Aceite, especias y salsas","level":0,"order":7,"categories":[{"id":112,"name":"Aceite, vinagre y sal","level":1,"order":7,"categories":[{"id":424,"name":"Sal y bicarbonato","level":2,"order":7}]}]}],"extra_info":[null],"display_name":"Bicarbonato sódico Hacendado","is_variable_weight":false,"price_instructions":{"iva":10,"is_new":false,"is_pack":false,"pack_size":null,"unit_name":null,"unit_size":1.0,"bulk_price":"1.50","unit_price":"1.50","approx_size":false,"size_format":"kg","total_units":null,"unit_selector":true,"bunch_selector":false,"drained_weight":null,"selling_method":0,"price_decreased":false,"reference_price":"1.500","min_bunch_amount":1.0,"reference_format":"kg","increment_bunch_amount":1.0},"nutrition_information":{"allergens":null,"ingredients":"Bicarbonato sódico (E-500ii)"}}