{"id":"82732","ean":"8480000827326","slug":"magdalenas-integrales-0-azucares-anadidos-hacendado-paquete","brand":"Hacendado","limit":999,"badges":{"is_water":false,"requires_age_check":false},"origin":null,"photos":[{"zoom":"https://prod-mercadona.imgix.net/images/c8994fa8a2bba54f16bd3bbf5a6fc67f.jpg?fit=crop&h=1600&w=1600","regular":"https://prod-mercadona.imgix.net/images/c8994fa8a2bba54f16bd3bbf5a6fc67f.jpg?fit=crop&h=600&w=600","thumbnail":"https://prod-mercadona.imgix.net/images/c8994fa8a2bba54f16bd3bbf5a6fc67f.jpg?fit=crop&h=300&w=300","perspective":2},{"zoom":"https://prod-mercadona.imgix.net/images/0ecc28f6830195889e5c4dce28bb7c67.jpg?fit=crop&h=1600&w=1600","regular":"https://prod-mercadona.imgix.net/images/0ecc28f6830195889e5c4dce28bb7c67.jpg?fit=crop&h=600&w=600","thumbnail":"https://prod-mercadona.imgix.net/images/0ecc28f6830195889e5c4dce28bb7c67.jpg?fit=crop&h=300&w=300","perspective":9}],"details":{"brand":"Hacendado","origin":null,"suppliers":[{"name":"Dulmatesa S.L."}],"legal_name":"Magdalena Redonda Integral","description":"Magdalenas integrales 0% azúcares añadidos Hacendado","counter_info":null,"danger_mentions":null,"alcohol_by_volume":null,"mandatory_mentions":null,"production_variant":null,"usage_instructions":null,"storage_instructions":"Conservar en lugar fresco y seco"},"packaging":"Paquete","published":true,"share_url":"https://tienda.mercadona.es/product/82732/magdalenas-integrales-0-azucares-anadidos-hacendado-paquete","thumbnail":"https://prod-mercadona.imgix.net/images/c8994fa8a2bba54f16bd3bbf5a6fc67f.jpg?fit=crop&h=300&w=300","categories":[{"id":5,"name":"Panadería y pastelería","level":0,"order":511,"categories":[{"id":66,"name":"Bollería envasada","level":1,"order":511,"categories":[{"id":334,"name":"Bollería envasada","level":2,"order":511}]}]}],"extra_info":[null],"display_name":"Magdalenas integrales 0% azúcares añadidos Hacendado","is_variable_weight":false,"price_instructions":{"iva":10,"is_new":false,"is_pack":false,"pack_size":null,"unit_name":null,"unit_size":0.28,"bulk_price":"7.86","unit_price":"2.20","approx_size":false,"size_format":"kg","total_units":null,"unit_selector":true,"bunch_selector":false,"drained_weight":null,"selling_method":0,"price_decreased":false,"reference_price":"7.858","min_bunch_amount":1.0,"reference_format":"kg","increment_bunch_amount":1.0},"nutrition_information":{"allergens":"Puede contener <strong>huevos y productos a base de huevo</strong>. Puede contener <strong>frutos de cáscara</strong>. Puede contener <strong>cereales que contengan gluten</strong>. Puede contener <strong>mostaza y productos derivados</strong>. Contiene <strong>trigo y productos derivados</strong>.","ingredients":"Edulcorante (maltitol), <strong>huevo</strong> líquido pasteurizado, aceite de girasol, harina integral de <strong>trigo</strong> (14%), agua, almidón de <strong>trigo</strong>, fructo-oligosacáridos, almidón modificado, humectante (glicerina), emulgente (E471), <strong>gluten</strong> de <strong>trigo</strong>, gasificantes (E450, E500), sal, estabilizante (E415), corrector de acidez (E330) y conservador (E202).  Puede contener trazas de <strong>frutos de cáscara</strong>, <strong>leche</strong> (incluida la <strong>lactosa</strong>), <strong>soja</strong> y <strong>mostaza</strong>."}}