{"id":"17572","ean":"7300400482615","slug":"pan-tostado-fino-con-sesamo-sal-marina-delicate-crisp-wasa-paquete","brand":"Wasa","limit":999,"badges":{"is_water":false,"requires_age_check":false},"origin":null,"photos":[{"zoom":"https://prod-mercadona.imgix.net/images/dc28342be8c28a14264d7e15fc7301e2.jpg?fit=crop&h=3600&w=3600","regular":"https://prod-mercadona.imgix.net/images/dc28342be8c28a14264d7e15fc7301e2.jpg?fit=crop&h=600&w=600","thumbnail":"https://prod-mercadona.imgix.net/images/dc28342be8c28a14264d7e15fc7301e2.jpg?fit=crop&h=300&w=300","perspective":1},{"zoom":"https://prod-mercadona.imgix.net/images/84fa418adfec279364188e8330a5d8ac.jpg?fit=crop&h=3600&w=3600","regular":"https://prod-mercadona.imgix.net/images/84fa418adfec279364188e8330a5d8ac.jpg?fit=crop&h=600&w=600","thumbnail":"https://prod-mercadona.imgix.net/images/84fa418adfec279364188e8330a5d8ac.jpg?fit=crop&h=300&w=300","perspective":9}],"status":null,"details":{"brand":"Wasa","origin":null,"suppliers":[{"name":"Barilla Sverige AB,"}],"legal_name":"Producto de panadería con harina de trigo integral y semillas de sésamo","description":"Pan tostado fino con sésamo y sal marina Delicate Crisp Wasa","counter_info":null,"danger_mentions":"","alcohol_by_volume":null,"mandatory_mentions":"","production_variant":"","usage_instructions":"Listo para degustar. Conservar en un lugar fresco y seco. Consumir preferentemente antes del: ver fecha en el lateral.","storage_instructions":"Consérvese en un lugar seco y oscuro.","is_prepared_by_mercadona":false},"is_bulk":false,"packaging":"Paquete","published":true,"share_url":"https://tienda.mercadona.es/product/17572/pan-tostado-fino-con-sesamo-sal-marina-delicate-crisp-wasa-paquete","thumbnail":"https://prod-mercadona.imgix.net/images/dc28342be8c28a14264d7e15fc7301e2.jpg?fit=crop&h=300&w=300","categories":[{"id":5,"name":"Panadería y pastelería","level":0,"order":515,"categories":[{"id":62,"name":"Pan tostado y rallado","level":1,"order":515,"categories":[{"id":322,"name":"Pan tostado","level":2,"order":515}]}]}],"extra_info":[""],"display_name":"Pan tostado fino con sésamo y sal marina Delicate Crisp Wasa","unavailable_from":null,"is_variable_weight":false,"price_instructions":{"iva":null,"is_new":false,"is_pack":false,"pack_size":null,"unit_name":null,"unit_size":0.19,"bulk_price":"9.47","unit_price":"1.80","approx_size":false,"size_format":"kg","total_units":null,"unit_selector":true,"bunch_selector":false,"drained_weight":null,"selling_method":0,"tax_percentage":"4.000","price_decreased":false,"reference_price":"9.474","min_bunch_amount":1.0,"reference_format":"kg","previous_unit_price":null,"increment_bunch_amount":1.0},"unavailable_weekdays":[],"nutrition_information":{"allergens":"Contiene <strong>trigo y productos derivados</strong>. Contiene <strong>gb</strong>. Contiene <strong>cereales que contengan gluten</strong>. Contiene <strong>granos de sésamo y productos a base de granos de sésamo</strong>.","ingredients":"harina de <strong>trigo</strong> integral, harina de <strong>trigo</strong>, granos de <strong>sésamo</strong> (13%), aceite de colza, sal marina (1,4%), extracto de malta dec<strong>ebada,</strong> sal, levadura, antioxidante: extractos de romero."},"is_new_arrival":true}